ckanext_tif_imageview-1.0.3-nspkg.pth
ckanext/tif_imageview/__init__.py
ckanext/tif_imageview/plugin.py
ckanext/tif_imageview/tests/__init__.py
ckanext/tif_imageview/tests/test_plugin.py
ckanext/tif_imageview/theme/templates/tif_form.html
ckanext/tif_imageview/theme/templates/tif_view.html
ckanext_tif_imageview-1.0.3.dist-info/LICENSE
ckanext_tif_imageview-1.0.3.dist-info/METADATA
ckanext_tif_imageview-1.0.3.dist-info/WHEEL
ckanext_tif_imageview-1.0.3.dist-info/entry_points.txt
ckanext_tif_imageview-1.0.3.dist-info/namespace_packages.txt
ckanext_tif_imageview-1.0.3.dist-info/top_level.txt
ckanext_tif_imageview-1.0.3.dist-info/RECORD
