Metadata-Version: 2.1
Name: ckanext-tif-imageview
Version: 1.0.3
Summary: A ckan extension for showing TIF images as resource preview
Home-page: https://github.com/TIBHannover/ckanext-tif-imageview
Author: Pooya Oladazimi, Technische Informationsbibliothek(TIB)
Author-email: pooya.oladazimi@tib.eu
License: AGPL
Keywords: CKAN
Platform: UNKNOWN
Classifier: Development Status :: 3 - Alpha
Classifier: License :: OSI Approved :: GNU Affero General Public License v3 or later (AGPLv3+)
Classifier: Programming Language :: Python :: 3
